md2typst/__init__.py
md2typst/ast.py
md2typst/config.py
md2typst/generator.py
md2typst/parsers/__init__.py
md2typst/parsers/base.py
md2typst/parsers/markdown_it.py
md2typst/parsers/marko.py
md2typst/parsers/mistune.py
md2typst-0.2.0.dist-info/WHEEL
md2typst-0.2.0.dist-info/entry_points.txt
md2typst-0.2.0.dist-info/METADATA
md2typst-0.2.0.dist-info/RECORD
