Metadata-Version: 2.3
Name: md2typst
Version: 0.2.0
Summary: Markdown to Typst converter with multiple parser support
Author: Stefane Fermigier
Author-email: Stefane Fermigier <sf@abilian.com>
Requires-Dist: markdown-it-py>=3.0.0
Requires-Dist: click>=8.0.0
Requires-Dist: mistune>=3.0.0
Requires-Dist: marko>=2.0.0
Requires-Python: >=3.12
